./.gitignore
./PKG-INFO
./README.md
./py.typed
./pyproject.toml
./tests/test_bench.py
./tests/test_performance.py
./tests/test_vad.py
./vision_agents/plugins/silero/__init__.py
./vision_agents/plugins/silero/vad.py
vision_agents_plugins_silero-0.1.9.dist-info/METADATA
vision_agents_plugins_silero-0.1.9.dist-info/WHEEL
vision_agents_plugins_silero-0.1.9.dist-info/RECORD
