Metadata-Version: 2.4
Name: vision-agents-plugins-silero
Version: 0.1.9
Summary: Silero plugin for GetStream
Project-URL: Documentation, https://visionagents.ai/
Project-URL: Website, https://visionagents.ai/
Project-URL: Source, https://github.com/GetStream/Vision-Agents
License-Expression: MIT
Requires-Python: >=3.10
Requires-Dist: numpy<2.3,>=2.2.6
Requires-Dist: silero>=0.4.1
Requires-Dist: torch>=2.7.1
Requires-Dist: vision-agents
